{
  "similarity_threshold": 0.45,
  "papers": [
    {
      "id": 0,
      "title": "A Survey on Deep Learning in Medical Image Analysis"
    },
    {
      "id": 1,
      "title": "Machine learning applied in maternal and fetal health: a narrative review focused on pregnancy diseases and complications"
    },
    {
      "id": 2,
      "title": "Application of Machine and Deep Learning Algorithms in Intelligent Clinical Decision Support Systems in Healthcare"
    },
    {
      "id": 3,
      "title": "Machine learning of big data in gaining insight into successful treatment of hypertension"
    },
    {
      "id": 4,
      "title": "Machine learning for personalized medicine: Tailoring treatment strategies through data analysis"
    },
    {
      "id": 5,
      "title": "Large clinical databases for the study of lung cancer: Making up for the failure of randomized trials"
    },
    {
      "id": 6,
      "title": "Sharpening the resolution on data matters: a brief roadmap for understanding deep learning for medical data"
    },
    {
      "id": 7,
      "title": "Machine Learning Techniques for Personalised Medicine Approaches in Immune-Mediated Chronic Inflammatory Diseases: Applications and Challenges"
    },
    {
      "id": 8,
      "title": "Artificial Intelligence In Healthcare: A Review Of Deep Learning Models For Medical Image Analysis"
    },
    {
      "id": 9,
      "title": "Deep learning methods for cancer recognition"
    },
    {
      "id": 10,
      "title": "Opportunities and obstacles for deep learning in biology and medicine"
    },
    {
      "id": 11,
      "title": "Recent Applications of Deep Learning Algorithms in Medical Image Analysis"
    },
    {
      "id": 12,
      "title": "Revolutionizing Healthcare: How Deep Learning is poised to Change the Landscape of Medical Diagnosis and Treatment"
    },
    {
      "id": 13,
      "title": "Deep Learning in Medical Imaging"
    },
    {
      "id": 14,
      "title": "Machine learning y el control de hipertensi\u00f3n arterial"
    },
    {
      "id": 15,
      "title": "Genie Out of the Bottle: Is There a Role for Gene-Gene Interactions in Early Detection of Lung Cancer?"
    },
    {
      "id": 16,
      "title": "Machine learning&apos;s role in personalized medicine &amp; treatment optimization"
    },
    {
      "id": 17,
      "title": "Artificial Intelligence in Medical Imaging: Applications of Deep Learning for Disease Detection and Diagnosis"
    },
    {
      "id": 18,
      "title": "DeepHealth: Deep Learning for Health Informatics reviews, challenges, and opportunities on medical imaging, electronic health records, genomics, sensing, and online communication health"
    },
    {
      "id": 19,
      "title": "Deep Learning in Cardiology"
    },
    {
      "id": 20,
      "title": "Using Machine Learning to Individualize Treatment Effect Estimation: Challenges and Opportunities"
    },
    {
      "id": 21,
      "title": "The Transformative Impact of Deep Learning on Personalized Medicine"
    },
    {
      "id": 22,
      "title": "Deep Learning in Medical Imaging: General Overview"
    },
    {
      "id": 23,
      "title": "Machine Learning as a Novel Method to Support Therapeutic Drug Management and Precision Dosing"
    },
    {
      "id": 24,
      "title": "Big Data to Knowledge: Application of Machine Learning to Predictive Modeling of Therapeutic Response in Cancer"
    },
    {
      "id": 25,
      "title": "Deep Learning and Its Applications in Biomedicine"
    },
    {
      "id": 26,
      "title": "Machine Learning Applied to Diagnosis of Human Diseases: A Systematic Review"
    },
    {
      "id": 27,
      "title": "Deep learning for healthcare: review, opportunities and challenges"
    },
    {
      "id": 28,
      "title": "Attention Is All You Need"
    },
    {
      "id": 29,
      "title": "Deep learning in systems medicine"
    }
  ],
  "links": [
    {
      "source": 0,
      "target": 2,
      "similarity": 0.535669207572937
    },
    {
      "source": 0,
      "target": 4,
      "similarity": 0.4848780035972595
    },
    {
      "source": 0,
      "target": 6,
      "similarity": 0.5331401824951172
    },
    {
      "source": 0,
      "target": 8,
      "similarity": 0.7654505968093872
    },
    {
      "source": 0,
      "target": 9,
      "similarity": 0.7329760193824768
    },
    {
      "source": 0,
      "target": 10,
      "similarity": 0.7269595861434937
    },
    {
      "source": 0,
      "target": 11,
      "similarity": 0.7416827082633972
    },
    {
      "source": 0,
      "target": 12,
      "similarity": 0.6324609518051147
    },
    {
      "source": 0,
      "target": 13,
      "similarity": 0.7220577001571655
    },
    {
      "source": 0,
      "target": 17,
      "similarity": 0.8612253665924072
    },
    {
      "source": 0,
      "target": 18,
      "similarity": 0.5642597675323486
    },
    {
      "source": 0,
      "target": 19,
      "similarity": 0.7294760942459106
    },
    {
      "source": 0,
      "target": 21,
      "similarity": 0.6954021453857422
    },
    {
      "source": 0,
      "target": 22,
      "similarity": 0.6108334064483643
    },
    {
      "source": 0,
      "target": 25,
      "similarity": 0.7284659147262573
    },
    {
      "source": 0,
      "target": 26,
      "similarity": 0.5483498573303223
    },
    {
      "source": 0,
      "target": 27,
      "similarity": 0.6711645126342773
    },
    {
      "source": 0,
      "target": 29,
      "similarity": 0.5863862037658691
    },
    {
      "source": 1,
      "target": 2,
      "similarity": 0.5101431608200073
    },
    {
      "source": 1,
      "target": 4,
      "similarity": 0.49368613958358765
    },
    {
      "source": 1,
      "target": 6,
      "similarity": 0.5408278703689575
    },
    {
      "source": 1,
      "target": 13,
      "similarity": 0.4517822861671448
    },
    {
      "source": 1,
      "target": 16,
      "similarity": 0.5661212205886841
    },
    {
      "source": 1,
      "target": 23,
      "similarity": 0.45403194427490234
    },
    {
      "source": 1,
      "target": 24,
      "similarity": 0.45708227157592773
    },
    {
      "source": 1,
      "target": 25,
      "similarity": 0.48708975315093994
    },
    {
      "source": 1,
      "target": 26,
      "similarity": 0.6154919862747192
    },
    {
      "source": 2,
      "target": 4,
      "similarity": 0.641947329044342
    },
    {
      "source": 2,
      "target": 6,
      "similarity": 0.632486879825592
    },
    {
      "source": 2,
      "target": 7,
      "similarity": 0.5851396918296814
    },
    {
      "source": 2,
      "target": 8,
      "similarity": 0.636390209197998
    },
    {
      "source": 2,
      "target": 9,
      "similarity": 0.5040018558502197
    },
    {
      "source": 2,
      "target": 10,
      "similarity": 0.6667786836624146
    },
    {
      "source": 2,
      "target": 11,
      "similarity": 0.4673444926738739
    },
    {
      "source": 2,
      "target": 12,
      "similarity": 0.5752452611923218
    },
    {
      "source": 2,
      "target": 13,
      "similarity": 0.5296061038970947
    },
    {
      "source": 2,
      "target": 16,
      "similarity": 0.6071966290473938
    },
    {
      "source": 2,
      "target": 17,
      "similarity": 0.5880382657051086
    },
    {
      "source": 2,
      "target": 18,
      "similarity": 0.6274186372756958
    },
    {
      "source": 2,
      "target": 19,
      "similarity": 0.6359672546386719
    },
    {
      "source": 2,
      "target": 20,
      "similarity": 0.46682000160217285
    },
    {
      "source": 2,
      "target": 21,
      "similarity": 0.6582138538360596
    },
    {
      "source": 2,
      "target": 22,
      "similarity": 0.4782993197441101
    },
    {
      "source": 2,
      "target": 23,
      "similarity": 0.5559884309768677
    },
    {
      "source": 2,
      "target": 24,
      "similarity": 0.5416171550750732
    },
    {
      "source": 2,
      "target": 25,
      "similarity": 0.5997322797775269
    },
    {
      "source": 2,
      "target": 26,
      "similarity": 0.5986042618751526
    },
    {
      "source": 2,
      "target": 27,
      "similarity": 0.5646300911903381
    },
    {
      "source": 2,
      "target": 29,
      "similarity": 0.6486595273017883
    },
    {
      "source": 4,
      "target": 6,
      "similarity": 0.6204433441162109
    },
    {
      "source": 4,
      "target": 7,
      "similarity": 0.7031277418136597
    },
    {
      "source": 4,
      "target": 8,
      "similarity": 0.5983783006668091
    },
    {
      "source": 4,
      "target": 9,
      "similarity": 0.5471212863922119
    },
    {
      "source": 4,
      "target": 10,
      "similarity": 0.7248010635375977
    },
    {
      "source": 4,
      "target": 11,
      "similarity": 0.4748051166534424
    },
    {
      "source": 4,
      "target": 12,
      "similarity": 0.6144345998764038
    },
    {
      "source": 4,
      "target": 13,
      "similarity": 0.499774307012558
    },
    {
      "source": 4,
      "target": 16,
      "similarity": 0.8014229536056519
    },
    {
      "source": 4,
      "target": 17,
      "similarity": 0.5593668222427368
    },
    {
      "source": 4,
      "target": 18,
      "similarity": 0.6483668684959412
    },
    {
      "source": 4,
      "target": 19,
      "similarity": 0.5964019298553467
    },
    {
      "source": 4,
      "target": 20,
      "similarity": 0.5906119346618652
    },
    {
      "source": 4,
      "target": 21,
      "similarity": 0.6926882266998291
    },
    {
      "source": 4,
      "target": 23,
      "similarity": 0.6451571583747864
    },
    {
      "source": 4,
      "target": 24,
      "similarity": 0.6401636004447937
    },
    {
      "source": 4,
      "target": 25,
      "similarity": 0.6153126955032349
    },
    {
      "source": 4,
      "target": 26,
      "similarity": 0.6830958127975464
    },
    {
      "source": 4,
      "target": 27,
      "similarity": 0.7138988971710205
    },
    {
      "source": 4,
      "target": 29,
      "similarity": 0.6851906776428223
    },
    {
      "source": 6,
      "target": 7,
      "similarity": 0.6187740564346313
    },
    {
      "source": 6,
      "target": 8,
      "similarity": 0.630790114402771
    },
    {
      "source": 6,
      "target": 9,
      "similarity": 0.4770052433013916
    },
    {
      "source": 6,
      "target": 10,
      "similarity": 0.6355995535850525
    },
    {
      "source": 6,
      "target": 11,
      "similarity": 0.5103464126586914
    },
    {
      "source": 6,
      "target": 12,
      "similarity": 0.5975712537765503
    },
    {
      "source": 6,
      "target": 13,
      "similarity": 0.6026489734649658
    },
    {
      "source": 6,
      "target": 16,
      "similarity": 0.6307888031005859
    },
    {
      "source": 6,
      "target": 17,
      "similarity": 0.5904010534286499
    },
    {
      "source": 6,
      "target": 18,
      "similarity": 0.6369287967681885
    },
    {
      "source": 6,
      "target": 19,
      "similarity": 0.5664467811584473
    },
    {
      "source": 6,
      "target": 20,
      "similarity": 0.5099743008613586
    },
    {
      "source": 6,
      "target": 21,
      "similarity": 0.6952034831047058
    },
    {
      "source": 6,
      "target": 22,
      "similarity": 0.5377259850502014
    },
    {
      "source": 6,
      "target": 23,
      "similarity": 0.554638147354126
    },
    {
      "source": 6,
      "target": 24,
      "similarity": 0.5122254490852356
    },
    {
      "source": 6,
      "target": 25,
      "similarity": 0.5970442295074463
    },
    {
      "source": 6,
      "target": 26,
      "similarity": 0.6894087791442871
    },
    {
      "source": 6,
      "target": 27,
      "similarity": 0.5983411073684692
    },
    {
      "source": 6,
      "target": 29,
      "similarity": 0.5973936319351196
    },
    {
      "source": 7,
      "target": 8,
      "similarity": 0.5193953514099121
    },
    {
      "source": 7,
      "target": 10,
      "similarity": 0.5667569637298584
    },
    {
      "source": 7,
      "target": 12,
      "similarity": 0.4709726870059967
    },
    {
      "source": 7,
      "target": 16,
      "similarity": 0.6303313970565796
    },
    {
      "source": 7,
      "target": 17,
      "similarity": 0.4610670506954193
    },
    {
      "source": 7,
      "target": 18,
      "similarity": 0.6484612226486206
    },
    {
      "source": 7,
      "target": 19,
      "similarity": 0.4559210538864136
    },
    {
      "source": 7,
      "target": 20,
      "similarity": 0.5071892142295837
    },
    {
      "source": 7,
      "target": 21,
      "similarity": 0.6115444898605347
    },
    {
      "source": 7,
      "target": 23,
      "similarity": 0.604414701461792
    },
    {
      "source": 7,
      "target": 24,
      "similarity": 0.5565075874328613
    },
    {
      "source": 7,
      "target": 25,
      "similarity": 0.5042582750320435
    },
    {
      "source": 7,
      "target": 26,
      "similarity": 0.6518391370773315
    },
    {
      "source": 7,
      "target": 27,
      "similarity": 0.5714830160140991
    },
    {
      "source": 7,
      "target": 29,
      "similarity": 0.6157543659210205
    },
    {
      "source": 8,
      "target": 9,
      "similarity": 0.6442794799804688
    },
    {
      "source": 8,
      "target": 10,
      "similarity": 0.730701208114624
    },
    {
      "source": 8,
      "target": 11,
      "similarity": 0.6868391633033752
    },
    {
      "source": 8,
      "target": 12,
      "similarity": 0.7520147562026978
    },
    {
      "source": 8,
      "target": 13,
      "similarity": 0.700013279914856
    },
    {
      "source": 8,
      "target": 16,
      "similarity": 0.5587012767791748
    },
    {
      "source": 8,
      "target": 17,
      "similarity": 0.8182048797607422
    },
    {
      "source": 8,
      "target": 18,
      "similarity": 0.6568209528923035
    },
    {
      "source": 8,
      "target": 19,
      "similarity": 0.7088841795921326
    },
    {
      "source": 8,
      "target": 21,
      "similarity": 0.8111732006072998
    },
    {
      "source": 8,
      "target": 22,
      "similarity": 0.644356369972229
    },
    {
      "source": 8,
      "target": 24,
      "similarity": 0.47517624497413635
    },
    {
      "source": 8,
      "target": 25,
      "similarity": 0.740699052810669
    },
    {
      "source": 8,
      "target": 26,
      "similarity": 0.5210146307945251
    },
    {
      "source": 8,
      "target": 27,
      "similarity": 0.7470039129257202
    },
    {
      "source": 8,
      "target": 29,
      "similarity": 0.667544424533844
    },
    {
      "source": 9,
      "target": 10,
      "similarity": 0.6861979961395264
    },
    {
      "source": 9,
      "target": 11,
      "similarity": 0.6632325649261475
    },
    {
      "source": 9,
      "target": 12,
      "similarity": 0.5606674551963806
    },
    {
      "source": 9,
      "target": 13,
      "similarity": 0.6127676963806152
    },
    {
      "source": 9,
      "target": 16,
      "similarity": 0.4553455114364624
    },
    {
      "source": 9,
      "target": 17,
      "similarity": 0.7044088840484619
    },
    {
      "source": 9,
      "target": 18,
      "similarity": 0.5933509469032288
    },
    {
      "source": 9,
      "target": 19,
      "similarity": 0.6334835886955261
    },
    {
      "source": 9,
      "target": 21,
      "similarity": 0.6543612480163574
    },
    {
      "source": 9,
      "target": 22,
      "similarity": 0.5164915919303894
    },
    {
      "source": 9,
      "target": 24,
      "similarity": 0.544257402420044
    },
    {
      "source": 9,
      "target": 25,
      "similarity": 0.6374956369400024
    },
    {
      "source": 9,
      "target": 26,
      "similarity": 0.508029043674469
    },
    {
      "source": 9,
      "target": 27,
      "similarity": 0.5998028516769409
    },
    {
      "source": 9,
      "target": 29,
      "similarity": 0.5298024415969849
    },
    {
      "source": 10,
      "target": 11,
      "similarity": 0.6508413553237915
    },
    {
      "source": 10,
      "target": 12,
      "similarity": 0.7186601161956787
    },
    {
      "source": 10,
      "target": 13,
      "similarity": 0.599327027797699
    },
    {
      "source": 10,
      "target": 16,
      "similarity": 0.5845977067947388
    },
    {
      "source": 10,
      "target": 17,
      "similarity": 0.7277775406837463
    },
    {
      "source": 10,
      "target": 18,
      "similarity": 0.697924792766571
    },
    {
      "source": 10,
      "target": 19,
      "similarity": 0.7445635199546814
    },
    {
      "source": 10,
      "target": 21,
      "similarity": 0.7603513598442078
    },
    {
      "source": 10,
      "target": 22,
      "similarity": 0.5665120482444763
    },
    {
      "source": 10,
      "target": 23,
      "similarity": 0.5194666385650635
    },
    {
      "source": 10,
      "target": 24,
      "similarity": 0.5773226022720337
    },
    {
      "source": 10,
      "target": 25,
      "similarity": 0.7517555356025696
    },
    {
      "source": 10,
      "target": 26,
      "similarity": 0.6214497685432434
    },
    {
      "source": 10,
      "target": 27,
      "similarity": 0.8249748945236206
    },
    {
      "source": 10,
      "target": 28,
      "similarity": 0.46629127860069275
    },
    {
      "source": 10,
      "target": 29,
      "similarity": 0.7180936336517334
    },
    {
      "source": 11,
      "target": 12,
      "similarity": 0.5362187623977661
    },
    {
      "source": 11,
      "target": 13,
      "similarity": 0.7307449579238892
    },
    {
      "source": 11,
      "target": 17,
      "similarity": 0.8081226944923401
    },
    {
      "source": 11,
      "target": 18,
      "similarity": 0.556942880153656
    },
    {
      "source": 11,
      "target": 19,
      "similarity": 0.6430474519729614
    },
    {
      "source": 11,
      "target": 21,
      "similarity": 0.6251089572906494
    },
    {
      "source": 11,
      "target": 22,
      "similarity": 0.6210241317749023
    },
    {
      "source": 11,
      "target": 25,
      "similarity": 0.7022783160209656
    },
    {
      "source": 11,
      "target": 26,
      "similarity": 0.515631914138794
    },
    {
      "source": 11,
      "target": 27,
      "similarity": 0.6333082318305969
    },
    {
      "source": 11,
      "target": 29,
      "similarity": 0.5536309480667114
    },
    {
      "source": 12,
      "target": 13,
      "similarity": 0.5857468247413635
    },
    {
      "source": 12,
      "target": 16,
      "similarity": 0.6411042213439941
    },
    {
      "source": 12,
      "target": 17,
      "similarity": 0.6626895666122437
    },
    {
      "source": 12,
      "target": 18,
      "similarity": 0.6145452260971069
    },
    {
      "source": 12,
      "target": 19,
      "similarity": 0.6506551504135132
    },
    {
      "source": 12,
      "target": 21,
      "similarity": 0.7421176433563232
    },
    {
      "source": 12,
      "target": 22,
      "similarity": 0.5287246704101562
    },
    {
      "source": 12,
      "target": 25,
      "similarity": 0.6449732184410095
    },
    {
      "source": 12,
      "target": 26,
      "similarity": 0.5015139579772949
    },
    {
      "source": 12,
      "target": 27,
      "similarity": 0.7172070741653442
    },
    {
      "source": 12,
      "target": 29,
      "similarity": 0.6024519801139832
    },
    {
      "source": 13,
      "target": 16,
      "similarity": 0.46332117915153503
    },
    {
      "source": 13,
      "target": 17,
      "similarity": 0.8132941722869873
    },
    {
      "source": 13,
      "target": 18,
      "similarity": 0.5767170190811157
    },
    {
      "source": 13,
      "target": 19,
      "similarity": 0.6354148387908936
    },
    {
      "source": 13,
      "target": 21,
      "similarity": 0.6746827363967896
    },
    {
      "source": 13,
      "target": 22,
      "similarity": 0.7885713577270508
    },
    {
      "source": 13,
      "target": 25,
      "similarity": 0.7579391002655029
    },
    {
      "source": 13,
      "target": 26,
      "similarity": 0.5848588943481445
    },
    {
      "source": 13,
      "target": 27,
      "similarity": 0.6222201585769653
    },
    {
      "source": 13,
      "target": 29,
      "similarity": 0.5900760889053345
    },
    {
      "source": 16,
      "target": 17,
      "similarity": 0.49407291412353516
    },
    {
      "source": 16,
      "target": 18,
      "similarity": 0.6049392223358154
    },
    {
      "source": 16,
      "target": 19,
      "similarity": 0.5204529762268066
    },
    {
      "source": 16,
      "target": 20,
      "similarity": 0.5592913627624512
    },
    {
      "source": 16,
      "target": 21,
      "similarity": 0.6513204574584961
    },
    {
      "source": 16,
      "target": 23,
      "similarity": 0.6013237237930298
    },
    {
      "source": 16,
      "target": 24,
      "similarity": 0.6048291921615601
    },
    {
      "source": 16,
      "target": 25,
      "similarity": 0.5138823986053467
    },
    {
      "source": 16,
      "target": 26,
      "similarity": 0.6907303333282471
    },
    {
      "source": 16,
      "target": 27,
      "similarity": 0.5738398432731628
    },
    {
      "source": 16,
      "target": 29,
      "similarity": 0.6444861888885498
    },
    {
      "source": 17,
      "target": 18,
      "similarity": 0.6252155303955078
    },
    {
      "source": 17,
      "target": 19,
      "similarity": 0.7694525718688965
    },
    {
      "source": 17,
      "target": 21,
      "similarity": 0.7680161595344543
    },
    {
      "source": 17,
      "target": 22,
      "similarity": 0.6743580102920532
    },
    {
      "source": 17,
      "target": 25,
      "similarity": 0.7618408203125
    },
    {
      "source": 17,
      "target": 26,
      "similarity": 0.577511191368103
    },
    {
      "source": 17,
      "target": 27,
      "similarity": 0.7010548114776611
    },
    {
      "source": 17,
      "target": 29,
      "similarity": 0.6337236762046814
    },
    {
      "source": 18,
      "target": 19,
      "similarity": 0.6152780055999756
    },
    {
      "source": 18,
      "target": 21,
      "similarity": 0.6949799656867981
    },
    {
      "source": 18,
      "target": 22,
      "similarity": 0.5133619904518127
    },
    {
      "source": 18,
      "target": 23,
      "similarity": 0.5852636098861694
    },
    {
      "source": 18,
      "target": 24,
      "similarity": 0.6022881269454956
    },
    {
      "source": 18,
      "target": 25,
      "similarity": 0.6744293570518494
    },
    {
      "source": 18,
      "target": 26,
      "similarity": 0.601037323474884
    },
    {
      "source": 18,
      "target": 27,
      "similarity": 0.7168392539024353
    },
    {
      "source": 18,
      "target": 29,
      "similarity": 0.6713700890541077
    },
    {
      "source": 19,
      "target": 21,
      "similarity": 0.700975775718689
    },
    {
      "source": 19,
      "target": 22,
      "similarity": 0.5847654342651367
    },
    {
      "source": 19,
      "target": 24,
      "similarity": 0.4876266419887543
    },
    {
      "source": 19,
      "target": 25,
      "similarity": 0.7594775557518005
    },
    {
      "source": 19,
      "target": 26,
      "similarity": 0.5431772470474243
    },
    {
      "source": 19,
      "target": 27,
      "similarity": 0.7401021718978882
    },
    {
      "source": 19,
      "target": 29,
      "similarity": 0.653579831123352
    },
    {
      "source": 20,
      "target": 23,
      "similarity": 0.5036427974700928
    },
    {
      "source": 20,
      "target": 24,
      "similarity": 0.45872849225997925
    },
    {
      "source": 20,
      "target": 26,
      "similarity": 0.5057191252708435
    },
    {
      "source": 20,
      "target": 29,
      "similarity": 0.45342570543289185
    },
    {
      "source": 21,
      "target": 22,
      "similarity": 0.6231000423431396
    },
    {
      "source": 21,
      "target": 23,
      "similarity": 0.5033109188079834
    },
    {
      "source": 21,
      "target": 24,
      "similarity": 0.5809906721115112
    },
    {
      "source": 21,
      "target": 25,
      "similarity": 0.7429932355880737
    },
    {
      "source": 21,
      "target": 26,
      "similarity": 0.578360915184021
    },
    {
      "source": 21,
      "target": 27,
      "similarity": 0.7241518497467041
    },
    {
      "source": 21,
      "target": 29,
      "similarity": 0.6843785047531128
    },
    {
      "source": 22,
      "target": 25,
      "similarity": 0.7017917633056641
    },
    {
      "source": 22,
      "target": 27,
      "similarity": 0.615270733833313
    },
    {
      "source": 22,
      "target": 29,
      "similarity": 0.5489572286605835
    },
    {
      "source": 23,
      "target": 24,
      "similarity": 0.5797121524810791
    },
    {
      "source": 23,
      "target": 25,
      "similarity": 0.4588031768798828
    },
    {
      "source": 23,
      "target": 26,
      "similarity": 0.5576566457748413
    },
    {
      "source": 23,
      "target": 27,
      "similarity": 0.4915573000907898
    },
    {
      "source": 23,
      "target": 29,
      "similarity": 0.5638636946678162
    },
    {
      "source": 24,
      "target": 25,
      "similarity": 0.5211578011512756
    },
    {
      "source": 24,
      "target": 26,
      "similarity": 0.5566844940185547
    },
    {
      "source": 24,
      "target": 27,
      "similarity": 0.5555801391601562
    },
    {
      "source": 24,
      "target": 29,
      "similarity": 0.5716325640678406
    },
    {
      "source": 25,
      "target": 26,
      "similarity": 0.6190086603164673
    },
    {
      "source": 25,
      "target": 27,
      "similarity": 0.7674237489700317
    },
    {
      "source": 25,
      "target": 29,
      "similarity": 0.6521182060241699
    },
    {
      "source": 26,
      "target": 27,
      "similarity": 0.5885515213012695
    },
    {
      "source": 26,
      "target": 29,
      "similarity": 0.629540741443634
    },
    {
      "source": 27,
      "target": 29,
      "similarity": 0.7303269505500793
    }
  ]
}